svo_chunker/__init__.py
svo_chunker/svo_chunker.py
svo_chunker-0.1.0.dist-info/licenses/LICENSE
utils/__init__.py
utils/chunk_boundary_compare.py
utils/chunk_text_cli.py
svo_chunker-0.1.0.dist-info/METADATA
svo_chunker-0.1.0.dist-info/WHEEL
svo_chunker-0.1.0.dist-info/top_level.txt
svo_chunker-0.1.0.dist-info/RECORD
