Metadata-Version: 2.4
Name: svo-chunker
Version: 0.1.0
Summary: Semantic text chunking based on SVO triplets and vector proximity
Home-page: https://github.com/maverikod/vvz-svo-chunker
Author: Your Name
Author-email: your.email@example.com
Classifier: Programming Language :: Python :: 3
Classifier: License :: OSI Approved :: MIT License
Classifier: Operating System :: OS Independent
Classifier: Natural Language :: Russian
Classifier: Natural Language :: English
Requires-Python: >=3.7
License-File: LICENSE
Requires-Dist: langdetect
Requires-Dist: spacy
Requires-Dist: stanza
Requires-Dist: natasha
Requires-Dist: numpy
Requires-Dist: scipy
Dynamic: author
Dynamic: author-email
Dynamic: classifier
Dynamic: description
Dynamic: description-content-type
Dynamic: home-page
Dynamic: license-file
Dynamic: requires-dist
Dynamic: requires-python
Dynamic: summary
